{
  "user_id": "messi",
  "travel_style": [
    "adventure",
    "nature",
    "cultural"
  ],
  "property_preferences": [
    "hostel",
    "resort",
    "hotel"
  ],
  "typical_budget": "budget",
  "must_have_amenities": [
    "wifi",
    "spa",
    "pool",
    "room service"
  ],
  "preferred_vibes": [
    "quiet",
    "family-friendly",
    "cozy"
  ],
  "typical_companions": [
    "solo"
  ],
  "accessibility_needs": [],
  "location_preferences": [
    "beach",
    "mountains",
    "lake",
    "historic district"
  ],
  "custom_interests": "F1, Anime",
  "dietary_preferences": [
    "vegetarian",
    "vegan"
  ],
  "created_at": "2026-03-11T14:27:26.381587",
  "updated_at": "2026-03-11T14:27:26.381642"
}